{
  "problem_id": "003",
  "problem_name": "003_LogSoftmax",
  "results": [
    {
      "rank": 1,
      "user": "team_91",
      "github": "PRO-2684/AICS-openoperator",
      "score": 0.7342744506862434,
      "latency": 48.95580932497978,
      "timestamp": "2026-05-18T02:56:28.948070+00:00"
    },
    {
      "rank": 2,
      "user": "team_42",
      "github": "PRO-2684/AICS-openoperator",
      "score": 0.7199053503085512,
      "latency": 49.93295297026634,
      "timestamp": "2026-05-18T02:37:26.209937+00:00"
    },
    {
      "rank": 3,
      "user": "cuda组",
      "github": "AICS-2025-63H/openoperator",
      "score": 0.6282940086847559,
      "latency": 57.21366032958031,
      "timestamp": "2026-05-17T16:49:21.975863+00:00"
    },
    {
      "rank": 4,
      "user": "二十五组",
      "github": "cotangents/openoperator-start-kit-team25",
      "score": 0.5181427060852756,
      "latency": 69.376640021801,
      "timestamp": "2026-05-17T14:58:31.097930+00:00"
    },
    {
      "rank": 5,
      "user": "智算第九组",
      "github": "silent-Ning9/BangC09",
      "score": 0.4224502125760317,
      "latency": 85.09168401360512,
      "timestamp": "2026-05-17T15:27:44.916502+00:00"
    },
    {
      "rank": 6,
      "user": "team_48",
      "github": "zhangxingyin/ICS_18Team",
      "score": 0.38387586921346706,
      "latency": 93.64224970340729,
      "timestamp": "2026-05-18T02:07:46.582839+00:00"
    },
    {
      "rank": 7,
      "user": "888",
      "github": "RuixiZhang0906/888-op-gen",
      "score": 0.38059183778494743,
      "latency": 94.45026516914368,
      "timestamp": "2026-05-17T13:38:16.868357+00:00"
    },
    {
      "rank": 8,
      "user": "team_21",
      "github": "zhiyuanSo/ICS_13Team",
      "score": 0.12026967291739464,
      "latency": 298.88665303587914,
      "timestamp": "2026-05-17T15:30:44.015230+00:00"
    },
    {
      "rank": 9,
      "user": "随缘组",
      "github": "xufeng102403/operator",
      "score": 0.0848794046564684,
      "latency": 423.5067404806614,
      "timestamp": "2026-05-17T14:16:15.323591+00:00"
    },
    {
      "rank": 10,
      "user": "team_55",
      "github": "geotle77/AICS-BangC_Game-17",
      "score": 0.07813335117546392,
      "latency": 460.07242053747177,
      "timestamp": "2026-05-18T04:37:41.678157+00:00"
    },
    {
      "rank": 11,
      "user": "智算第八组",
      "github": "beiwenziyao/BANGC08",
      "score": 0.050686429742666336,
      "latency": 709.2036306858063,
      "timestamp": "2026-05-17T13:33:53.886254+00:00"
    },
    {
      "rank": 12,
      "user": "team_37",
      "github": "mygitljf/openoperator-mvp",
      "score": 0.040965379145424044,
      "latency": 877.4970658123493,
      "timestamp": "2026-05-17T14:28:49.658531+00:00"
    },
    {
      "rank": 13,
      "user": "智算第七组",
      "github": "laomaer/BANGC07",
      "score": 0.03896168782308931,
      "latency": 922.6243011653423,
      "timestamp": "2026-05-17T14:55:24.867648+00:00"
    },
    {
      "rank": 14,
      "user": "team_29",
      "github": "duroey/openoperator-basic",
      "score": 0.018109721119869596,
      "latency": 1984.9560223519802,
      "timestamp": "2026-05-17T14:30:31.808698+00:00"
    },
    {
      "rank": 15,
      "user": "team_18",
      "github": "wbr258/openoperator-start-kit",
      "score": 0.010822413641765798,
      "latency": 3321.5326257050037,
      "timestamp": "2026-05-17T14:54:19.768244+00:00"
    },
    {
      "rank": 16,
      "user": "算不懂",
      "github": "caozhining/suanbudong_openoperator",
      "score": 0.010666315012088997,
      "latency": 3370.1423555612564,
      "timestamp": "2026-05-17T14:07:33.143344+00:00"
    },
    {
      "rank": 17,
      "user": "team_70",
      "github": "SilWhite/ICS-Competition",
      "score": 0.010542782237667157,
      "latency": 3409.63127091527,
      "timestamp": "2026-05-17T17:15:47.803387+00:00"
    },
    {
      "rank": 18,
      "user": "team_90",
      "github": "sleepy3dog/AICS-38",
      "score": 0.010257111386715168,
      "latency": 3504.592925310135,
      "timestamp": "2026-05-17T15:06:29.383355+00:00"
    },
    {
      "rank": 19,
      "user": "team_67",
      "github": "Auro-sol/BangC68",
      "score": 0.010161435821033741,
      "latency": 3537.590615451336,
      "timestamp": "2026-05-17T14:38:25.312672+00:00"
    },
    {
      "rank": 20,
      "user": "team_8",
      "github": "ykkkx/ICS_28",
      "score": 0.006086825501401375,
      "latency": 5905.705690383911,
      "timestamp": "2026-05-17T14:38:21.059749+00:00"
    },
    {
      "rank": 21,
      "user": "team_72",
      "github": "ifbluerain/kernel-competition-bot-openoperator-start-kit",
      "score": 0.0014457718212306605,
      "latency": 24863.536190241575,
      "timestamp": "2026-05-17T14:27:01.538924+00:00"
    },
    {
      "rank": 22,
      "user": "养老组",
      "github": "Ace-Eternal/op_retirement",
      "score": 0.001445004302945309,
      "latency": 24876.742530614138,
      "timestamp": "2026-05-17T13:26:25.435197+00:00"
    },
    {
      "rank": 23,
      "user": "team_73",
      "github": "dingyue772/TensorCraft",
      "score": 0.0014254109003487675,
      "latency": 25218.69307383895,
      "timestamp": "2026-05-17T15:03:29.379145+00:00"
    },
    {
      "rank": 24,
      "user": "team_86",
      "github": "RachelGu2003/ICS_86Team",
      "score": 0.001424369974427668,
      "latency": 25237.1228300035,
      "timestamp": "2026-05-17T13:31:52.734223+00:00"
    },
    {
      "rank": 25,
      "user": "team_12",
      "github": "yinuo222/kernel-competition-group40",
      "score": 0.0012926004503920766,
      "latency": 27809.83094125986,
      "timestamp": "2026-05-17T14:22:11.669708+00:00"
    }
  ],
  "last_updated": "2026-05-18T04:42:42.643464+00:00"
}