{
  "problem_id": "007",
  "problem_name": "007_conv_depthwise_separable_2D",
  "results": [
    {
      "rank": 1,
      "user": "team_91",
      "github": "PRO-2684/AICS-openoperator",
      "score": 0.8335918440333616,
      "latency": 1677.4156441291173,
      "timestamp": "2026-06-04T16:50:13.597000+00:00",
      "commit_sha": "2c74dee02014f1bb458b0dd79fdc4990bf00c377"
    },
    {
      "rank": 2,
      "user": "team_42",
      "github": "PRO-2684/AICS-openoperator",
      "score": 0.8324163962259146,
      "latency": 1679.7843078772228,
      "timestamp": "2026-06-04T16:52:10.590919+00:00"
    },
    {
      "rank": 3,
      "user": "cuda组",
      "github": "AICS-2025-63H/openoperator",
      "score": 0.22887538712624791,
      "latency": 6109.350671370824,
      "timestamp": "2026-05-18T08:43:30.078519+00:00",
      "commit_sha": "209ef8470eb2725e187f203aba1cb369078376f1"
    },
    {
      "rank": 4,
      "user": "team_43",
      "github": "Demoxxy/smart_openoperator-start-kit",
      "score": 0.22343225338852218,
      "latency": 6258.183314154546,
      "timestamp": "2026-05-18T16:07:28.064982+00:00",
      "commit_sha": "4734ab5a90f871d7dd48f48555af354faa54da84"
    },
    {
      "rank": 5,
      "user": "team_37",
      "github": "mygitljf/openoperator-mvp",
      "score": 0.19121102610434867,
      "latency": 7312.75820483764,
      "timestamp": "2026-05-18T06:19:20.174287+00:00",
      "commit_sha": "414c1c3239a98642ca0fbacc5d2ab42cbdd48798"
    },
    {
      "rank": 6,
      "user": "team_48",
      "github": "zhangxingyin/ICS_18Team",
      "score": 0.18567880724095112,
      "latency": 7530.638637642066,
      "timestamp": "2026-05-18T14:36:40.112566+00:00",
      "commit_sha": "51d32f3ebb48b76af3c561c633bc3a05d31b462f"
    },
    {
      "rank": 7,
      "user": "team_8",
      "github": "ykkkx/ICS_28",
      "score": 0.12260250757258558,
      "latency": 11404.986958950758,
      "timestamp": "2026-05-23T14:54:59.341666+00:00"
    },
    {
      "rank": 8,
      "user": "三十二组",
      "github": "zhengbanlinyi/BangC32",
      "score": 0.08913290861138456,
      "latency": 15687.584100912014,
      "timestamp": "2026-06-04T05:50:05.439623+00:00"
    },
    {
      "rank": 9,
      "user": "team_90",
      "github": "sleepy3dog/AICS-38",
      "score": 0.05565575924769042,
      "latency": 25123.725179582834,
      "timestamp": "2026-06-02T02:48:27.207591+00:00",
      "commit_sha": "be1bf3d864a6c4c3ed194e5124dd4be8757efed6"
    },
    {
      "rank": 10,
      "user": "team_2",
      "github": "HT1108/BangcOperator",
      "score": 0.04082475758297666,
      "latency": 34250.78513100743,
      "timestamp": "2026-06-04T15:48:00.049844+00:00"
    },
    {
      "rank": 11,
      "user": "智算第七组",
      "github": "laomaer/BANGC07",
      "score": 0.027309695615011714,
      "latency": 51200.863594810166,
      "timestamp": "2026-05-19T08:50:11.391853+00:00",
      "commit_sha": "f122e2d4be317dbc2583429d9684039eb0340cf9"
    },
    {
      "rank": 12,
      "user": "智算第八组",
      "github": "beiwenziyao/BANGC08",
      "score": 0.02249317480161031,
      "latency": 62164.63493183255,
      "timestamp": "2026-05-18T05:52:27.210509+00:00",
      "commit_sha": "27c1dc787edea7513b46d9215d43ed365fc22fb0"
    },
    {
      "rank": 13,
      "user": "智算第十组",
      "github": "koross49/openoperator-start-kit",
      "score": 0.0034424871915542635,
      "latency": 406183.0653809011,
      "timestamp": "2026-06-03T09:09:19.329838+00:00"
    },
    {
      "rank": 14,
      "user": "不知道叫什么名字组",
      "github": "luoluoluoluoli/Luoluoli_ice1",
      "score": 0.003210179353848268,
      "latency": 435576.90891126794,
      "timestamp": "2026-06-01T06:00:37.252023+00:00"
    },
    {
      "rank": 15,
      "user": "team_73",
      "github": "dingyue772/TensorCraft",
      "score": 0.0007401900608885014,
      "latency": 1889082.3774660628,
      "timestamp": "2026-05-29T07:11:34.114948+00:00"
    },
    {
      "rank": 16,
      "user": "team_18",
      "github": "wbr258/openoperator-start-kit",
      "score": 0.000402865049771117,
      "latency": 3470839.6789307394,
      "timestamp": "2026-06-04T11:08:18.838477+00:00"
    },
    {
      "rank": 17,
      "user": "team_80",
      "github": "MariyaSuwako/openoperator-start-kit",
      "score": 8.445101674701688e-05,
      "latency": 16557290.295138955,
      "timestamp": "2026-05-18T14:22:34.876040+00:00"
    }
  ],
  "last_updated": "2026-06-04T16:56:57.065929+00:00"
}