{
  "problem_id": "009",
  "problem_name": "009_conv_standard_1D",
  "results": [
    {
      "rank": 1,
      "user": "cuda组",
      "github": "AICS-2025-63H/openoperator",
      "score": 1.181449550360817,
      "latency": 60.80158054828644,
      "timestamp": "2026-05-17T15:08:23.292562+00:00"
    },
    {
      "rank": 2,
      "user": "team_48",
      "github": "zhangxingyin/ICS_18Team",
      "score": 0.6897556800041494,
      "latency": 104.14412245154381,
      "timestamp": "2026-05-17T13:38:34.266142+00:00"
    },
    {
      "rank": 3,
      "user": "智算第八组",
      "github": "beiwenziyao/BANGC08",
      "score": 0.5235013461322098,
      "latency": 137.21836730837822,
      "timestamp": "2026-05-17T13:35:21.087236+00:00"
    },
    {
      "rank": 4,
      "user": "team_67",
      "github": "Auro-sol/BangC68",
      "score": 0.14236931991433976,
      "latency": 504.5609548687935,
      "timestamp": "2026-05-17T14:51:16.565893+00:00"
    },
    {
      "rank": 5,
      "user": "team_37",
      "github": "mygitljf/openoperator-mvp",
      "score": 0.009086450187254373,
      "latency": 7905.617542564869,
      "timestamp": "2026-05-17T14:28:49.658531+00:00"
    },
    {
      "rank": 6,
      "user": "二十五组",
      "github": "cotangents/openoperator-start-kit-team25",
      "score": 0.0040687600084262626,
      "latency": 17655.01033514738,
      "timestamp": "2026-05-17T14:58:31.097930+00:00"
    },
    {
      "rank": 7,
      "user": "team_72",
      "github": "ifbluerain/kernel-competition-bot-openoperator-start-kit",
      "score": 0.0010834080487068373,
      "latency": 66303.73485386372,
      "timestamp": "2026-05-17T14:27:01.538924+00:00"
    },
    {
      "rank": 8,
      "user": "team_12",
      "github": "yinuo222/kernel-competition-group40",
      "score": 0.0010549346192574142,
      "latency": 68093.31942349672,
      "timestamp": "2026-05-17T14:28:57.798746+00:00"
    },
    {
      "rank": 9,
      "user": "养老组",
      "github": "Ace-Eternal/op_retirement",
      "score": 0.00105261144851339,
      "latency": 68243.60508471727,
      "timestamp": "2026-05-17T13:28:08.933744+00:00"
    },
    {
      "rank": 10,
      "user": "随缘组",
      "github": "xufeng102403/operator",
      "score": 0.0009995087123805945,
      "latency": 71869.30850148201,
      "timestamp": "2026-05-17T13:38:05.021386+00:00"
    },
    {
      "rank": 11,
      "user": "算不懂",
      "github": "caozhining/suanbudong_openoperator",
      "score": 0.0009953360147880454,
      "latency": 72170.60262337327,
      "timestamp": "2026-05-17T14:07:33.143344+00:00"
    },
    {
      "rank": 12,
      "user": "team_8",
      "github": "ykkkx/ICS_28",
      "score": 0.0009799439701264655,
      "latency": 73304.19104546309,
      "timestamp": "2026-05-17T14:38:21.059749+00:00"
    },
    {
      "rank": 13,
      "user": "team_18",
      "github": "wbr258/openoperator-start-kit",
      "score": 0.0009796068990150686,
      "latency": 73329.41414788365,
      "timestamp": "2026-05-17T14:29:53.598045+00:00"
    },
    {
      "rank": 14,
      "user": "team_90",
      "github": "sleepy3dog/AICS-38",
      "score": 0.0009672105740844999,
      "latency": 74269.24593746662,
      "timestamp": "2026-05-17T15:05:35.494190+00:00"
    },
    {
      "rank": 15,
      "user": "team_46",
      "github": "1LLLei/openoperator-start-kit_BangC_competition",
      "score": 0.00015427248733474147,
      "latency": 465630.65936788917,
      "timestamp": "2026-05-17T13:28:50.175123+00:00"
    },
    {
      "rank": 16,
      "user": "team_29",
      "github": "duroey/openoperator-basic",
      "score": 3.0637892078459386e-05,
      "latency": 2344612.998049706,
      "timestamp": "2026-05-17T14:30:31.808698+00:00"
    },
    {
      "rank": 17,
      "user": "team_86",
      "github": "RachelGu2003/ICS_86Team",
      "score": 2.5807269874114896e-05,
      "latency": 2783479.242492467,
      "timestamp": "2026-05-17T13:27:20.852428+00:00"
    },
    {
      "rank": 18,
      "user": "智能人工",
      "github": "asfdf-sudo/goodluck",
      "score": 9.780208896784061e-06,
      "latency": 7344832.892436534,
      "timestamp": "2026-05-17T14:44:26.838563+00:00"
    }
  ],
  "last_updated": "2026-05-17T15:08:55.699022+00:00"
}