{
  "problem_id": "018",
  "problem_name": "018_Matmul_with_diagonal_matrices_",
  "results": [
    {
      "rank": 1,
      "user": "team_25",
      "github": "zion-zion-zion/openoperator-start-kit",
      "score": 12.169301966833782,
      "latency": 518.6,
      "timestamp": "2026-04-28T18:41:56.877591+00:00"
    },
    {
      "rank": 2,
      "user": "team_48",
      "github": "zhangxingyin/ICS_18Team",
      "score": 11.301934097421205,
      "latency": 558.4,
      "timestamp": "2026-05-04T01:02:38.992378+00:00"
    }
  ],
  "last_updated": "2026-05-04T01:05:29.418023+00:00"
}