{
  "problem_id": "018",
  "problem_name": "018_Matmul_with_diagonal_matrices_",
  "results": [
    {
      "rank": 1,
      "user": "team_48",
      "github": "zhangxingyin/ICS_18Team",
      "score": 18.060680918129023,
      "latency": 350.7353365421295,
      "timestamp": "2026-05-17T14:10:45.774893+00:00"
    },
    {
      "rank": 2,
      "user": "team_42",
      "github": "PRO-2684/AICS-openoperator",
      "score": 17.89779448391943,
      "latency": 353.9273515343666,
      "timestamp": "2026-05-17T15:27:55.901810+00:00"
    },
    {
      "rank": 3,
      "user": "cuda组",
      "github": "AICS-2025-63H/openoperator",
      "score": 17.419154214900743,
      "latency": 363.6525012552738,
      "timestamp": "2026-05-17T15:07:32.213874+00:00"
    },
    {
      "rank": 4,
      "user": "team_91",
      "github": "PRO-2684/AICS-openoperator",
      "score": 17.044904726197338,
      "latency": 371.63710221648216,
      "timestamp": "2026-05-17T13:03:07.738975+00:00"
    },
    {
      "rank": 5,
      "user": "team_18",
      "github": "wbr258/openoperator-start-kit",
      "score": 7.708080503323713,
      "latency": 821.8023926019669,
      "timestamp": "2026-05-17T14:25:40.310171+00:00"
    },
    {
      "rank": 6,
      "user": "team_43",
      "github": "Demoxxy/smart_openoperator-start-kit",
      "score": 0.05346222613907444,
      "latency": 118485.88166758418,
      "timestamp": "2026-05-17T15:31:40.674694+00:00"
    },
    {
      "rank": 7,
      "user": "team_90",
      "github": "sleepy3dog/AICS-38",
      "score": 0.012106188366947405,
      "latency": 523246.36029079556,
      "timestamp": "2026-05-17T15:06:29.383355+00:00"
    }
  ],
  "last_updated": "2026-05-17T15:34:24.522042+00:00"
}