{
  "problem_id": "020",
  "problem_name": "020_Matmul_with_large_K_dimension_",
  "results": [
    {
      "rank": 1,
      "user": "team_91",
      "github": "PRO-2684/AICS-openoperator",
      "score": 0.16550935673359676,
      "latency": 10367.015097290277,
      "timestamp": "2026-05-17T15:21:59.111575+00:00"
    },
    {
      "rank": 2,
      "user": "team_42",
      "github": "PRO-2684/AICS-openoperator",
      "score": 0.15483537268059722,
      "latency": 11081.692576408386,
      "timestamp": "2026-05-17T16:19:09.580707+00:00"
    },
    {
      "rank": 3,
      "user": "cuda组",
      "github": "AICS-2025-63H/openoperator",
      "score": 0.10682486150605248,
      "latency": 16062.159836292267,
      "timestamp": "2026-05-17T16:49:14.130668+00:00"
    },
    {
      "rank": 4,
      "user": "智算第七组",
      "github": "laomaer/BANGC07",
      "score": 0.0018409217007175364,
      "latency": 932053.7637919188,
      "timestamp": "2026-05-17T14:48:10.547962+00:00"
    }
  ],
  "last_updated": "2026-05-17T16:50:36.313552+00:00"
}