{
  "problem_id": "040",
  "problem_name": "040_CosineSimilarityLoss",
  "results": [
    {
      "rank": 1,
      "user": "team_91",
      "github": "PRO-2684/AICS-openoperator",
      "score": 108.1,
      "latency": 2.0,
      "timestamp": "2026-05-04T07:34:04.594202+00:00"
    },
    {
      "rank": 2,
      "user": "team_42",
      "github": "PRO-2684/AICS-openoperator",
      "score": 108.1,
      "latency": 2.0,
      "timestamp": "2026-05-04T07:34:07.553144+00:00"
    },
    {
      "rank": 3,
      "user": "cuda组",
      "github": "AICS-2025-63H/openoperator",
      "score": 6.039106145251397,
      "latency": 35.8,
      "timestamp": "2026-05-04T19:03:19.119715+00:00"
    },
    {
      "rank": 4,
      "user": "team_25",
      "github": "zion-zion-zion/openoperator-start-kit",
      "score": 4.741228070175438,
      "latency": 45.6,
      "timestamp": "2026-04-29T20:12:15.088430+00:00"
    },
    {
      "rank": 5,
      "user": "不懂算子",
      "github": "HeiHuDie/openoperator-competition",
      "score": 4.376518218623482,
      "latency": 49.4,
      "timestamp": "2026-05-04T16:00:22.633046+00:00"
    },
    {
      "rank": 6,
      "user": "智算第九组",
      "github": "XLS233/BangC09",
      "score": 0.1912258977534053,
      "latency": 1130.6,
      "timestamp": "2026-04-30T02:34:41.218167+00:00"
    },
    {
      "rank": 7,
      "user": "算不懂",
      "github": "caozhining/suanbudong_openoperator",
      "score": 0.05248337136476186,
      "latency": 4119.4,
      "timestamp": "2026-04-30T12:45:11.675120+00:00"
    }
  ],
  "last_updated": "2026-05-04T19:05:08.398791+00:00"
}