{
  "problem_id": "046",
  "problem_name": "046_InstanceNorm",
  "results": [
    {
      "rank": 1,
      "user": "team_91",
      "github": "PRO-2684/AICS-openoperator",
      "score": 4.951349433349239,
      "latency": 1172.437146306038,
      "timestamp": "2026-05-17T13:03:07.738975+00:00"
    },
    {
      "rank": 2,
      "user": "cuda组",
      "github": "AICS-2025-63H/openoperator",
      "score": 4.585910355336783,
      "latency": 1265.8655643463135,
      "timestamp": "2026-05-17T15:13:43.139786+00:00"
    },
    {
      "rank": 3,
      "user": "team_55",
      "github": "geotle77/AICS-BangC_Game-17",
      "score": 3.9367881282904524,
      "latency": 1474.5893888175488,
      "timestamp": "2026-05-17T15:15:52.190247+00:00"
    },
    {
      "rank": 4,
      "user": "team_18",
      "github": "wbr258/openoperator-start-kit",
      "score": 3.7170909228873503,
      "latency": 1561.7444179952145,
      "timestamp": "2026-05-17T14:46:54.585114+00:00"
    },
    {
      "rank": 5,
      "user": "team_43",
      "github": "Demoxxy/smart_openoperator-start-kit",
      "score": 0.011461161183283037,
      "latency": 506505.9209242463,
      "timestamp": "2026-05-17T14:16:54.967044+00:00"
    },
    {
      "rank": 6,
      "user": "team_90",
      "github": "sleepy3dog/AICS-38",
      "score": 0.002104365845535851,
      "latency": 2758620.138373226,
      "timestamp": "2026-05-17T15:06:29.383355+00:00"
    }
  ],
  "last_updated": "2026-05-17T15:19:07.560479+00:00"
}