{
  "problem_id": "048",
  "problem_name": "048_Max_Pooling_2D",
  "results": [
    {
      "rank": 1,
      "user": "cuda组",
      "github": "AICS-2025-63H/openoperator",
      "score": 0.17817035433368514,
      "latency": 2944.1149284442267,
      "timestamp": "2026-05-18T07:09:39.211907+00:00"
    },
    {
      "rank": 2,
      "user": "team_70",
      "github": "SilWhite/ICS-Competition",
      "score": 0.03438717570079747,
      "latency": 15254.349603007237,
      "timestamp": "2026-05-18T06:52:15.751532+00:00"
    },
    {
      "rank": 3,
      "user": "team_48",
      "github": "zhangxingyin/ICS_18Team",
      "score": 0.03182050036477967,
      "latency": 16484.78163406253,
      "timestamp": "2026-05-18T07:52:08.493038+00:00"
    },
    {
      "rank": 4,
      "user": "team_18",
      "github": "wbr258/openoperator-start-kit",
      "score": 0.031453152128494095,
      "latency": 16677.311000724632,
      "timestamp": "2026-05-18T06:37:38.031756+00:00"
    },
    {
      "rank": 5,
      "user": "智算第八组",
      "github": "beiwenziyao/BANGC08",
      "score": 0.0009401549541919332,
      "latency": 557944.1959659258,
      "timestamp": "2026-05-18T06:23:54.424609+00:00"
    },
    {
      "rank": 6,
      "user": "智算第九组",
      "github": "XLS233/BangC09",
      "score": 0.00038254932406565657,
      "latency": 1371206.187022229,
      "timestamp": "2026-05-18T06:30:47.752002+00:00"
    }
  ],
  "last_updated": "2026-05-18T07:55:43.731284+00:00"
}