{
  "problem_id": "056",
  "problem_name": "056_gather",
  "results": [
    {
      "rank": 1,
      "user": "team_42",
      "github": "PRO-2684/AICS-openoperator",
      "score": 0.12945555995786928,
      "latency": 2081.046191354593,
      "timestamp": "2026-05-18T09:57:06.551327+00:00"
    },
    {
      "rank": 2,
      "user": "team_43",
      "github": "Demoxxy/smart_openoperator-start-kit",
      "score": 0.12429071905332746,
      "latency": 2167.523062477509,
      "timestamp": "2026-05-18T07:55:09.119177+00:00"
    },
    {
      "rank": 3,
      "user": "二十五组",
      "github": "cotangents/openoperator-start-kit-team25",
      "score": 0.12383605866294735,
      "latency": 2175.4810586571693,
      "timestamp": "2026-05-18T06:56:20.702270+00:00"
    },
    {
      "rank": 4,
      "user": "team_72",
      "github": "ifbluerain/kernel-competition-bot-openoperator-start-kit",
      "score": 0.12047277515151501,
      "latency": 2236.2147768338523,
      "timestamp": "2026-05-18T06:39:54.032879+00:00"
    },
    {
      "rank": 5,
      "user": "team_91",
      "github": "PRO-2684/AICS-openoperator",
      "score": 0.11890527643011373,
      "latency": 2265.694240729014,
      "timestamp": "2026-05-18T08:52:17.036007+00:00"
    },
    {
      "rank": 6,
      "user": "team_90",
      "github": "sleepy3dog/AICS-38",
      "score": 0.11537462858335057,
      "latency": 2335.0281020005546,
      "timestamp": "2026-05-18T09:20:52.999242+00:00"
    },
    {
      "rank": 7,
      "user": "cuda组",
      "github": "AICS-2025-63H/openoperator",
      "score": 0.11482358877557464,
      "latency": 2346.233930438757,
      "timestamp": "2026-05-18T09:41:07.584422+00:00"
    },
    {
      "rank": 8,
      "user": "team_18",
      "github": "wbr258/openoperator-start-kit",
      "score": 0.11424273477549109,
      "latency": 2358.1630860765777,
      "timestamp": "2026-05-18T09:19:32.058156+00:00"
    },
    {
      "rank": 9,
      "user": "team_12",
      "github": "yinuo222/kernel-competition-group40",
      "score": 0.11243333394656965,
      "latency": 2396.1132392287254,
      "timestamp": "2026-05-18T06:17:28.701402+00:00"
    },
    {
      "rank": 10,
      "user": "team_70",
      "github": "SilWhite/ICS-Competition",
      "score": 0.09525467975931627,
      "latency": 2828.2389976084232,
      "timestamp": "2026-05-18T09:16:37.878376+00:00"
    },
    {
      "rank": 11,
      "user": "team_29",
      "github": "duroey/openoperator-basic",
      "score": 0.0924006874124698,
      "latency": 2915.595192462206,
      "timestamp": "2026-05-18T07:49:22.593982+00:00"
    },
    {
      "rank": 12,
      "user": "team_37",
      "github": "mygitljf/openoperator-mvp",
      "score": 0.06263059301813131,
      "latency": 4301.460149387519,
      "timestamp": "2026-05-18T07:28:29.291604+00:00"
    },
    {
      "rank": 13,
      "user": "team_86",
      "github": "RachelGu2003/ICS_86Team",
      "score": 0.06150354370998088,
      "latency": 4380.28418769439,
      "timestamp": "2026-05-18T06:15:42.811653+00:00"
    },
    {
      "rank": 14,
      "user": "算不懂",
      "github": "caozhining/suanbudong_openoperator",
      "score": 0.05928166446724079,
      "latency": 4544.457420706749,
      "timestamp": "2026-05-18T06:16:54.463264+00:00"
    },
    {
      "rank": 15,
      "user": "team_21",
      "github": "zhiyuanSo/ICS_13Team",
      "score": 0.04347552297386014,
      "latency": 6196.659213552873,
      "timestamp": "2026-05-18T07:17:54.591242+00:00"
    },
    {
      "rank": 16,
      "user": "team_48",
      "github": "zhangxingyin/ICS_18Team",
      "score": 0.04174182508563556,
      "latency": 6454.03020704786,
      "timestamp": "2026-05-18T09:02:18.133797+00:00"
    },
    {
      "rank": 17,
      "user": "team_67",
      "github": "Auro-sol/BangC68",
      "score": 0.025403157876651043,
      "latency": 10605.09883488218,
      "timestamp": "2026-05-18T06:52:40.885207+00:00"
    },
    {
      "rank": 18,
      "user": "养老组",
      "github": "Ace-Eternal/op_retirement",
      "score": 0.009399264291966641,
      "latency": 28662.136911104124,
      "timestamp": "2026-05-18T05:48:26.245374+00:00"
    },
    {
      "rank": 19,
      "user": "随缘组",
      "github": "xufeng102403/operator",
      "score": 0.0034364160742179363,
      "latency": 78396.50210614006,
      "timestamp": "2026-05-18T06:01:42.693057+00:00"
    },
    {
      "rank": 20,
      "user": "智算第七组",
      "github": "laomaer/BANGC07",
      "score": 1.1411933741617002e-05,
      "latency": 23607129.70296542,
      "timestamp": "2026-05-18T07:59:43.266573+00:00"
    }
  ],
  "last_updated": "2026-05-18T09:57:44.019360+00:00"
}