{
  "problem_id": "057",
  "problem_name": "057_rotary_pos_emb_fusion",
  "results": [
    {
      "rank": 1,
      "user": "智算第七组",
      "github": "laomaer/BANGC07",
      "score": 0.05808305278093147,
      "latency": 3688.6146602531276,
      "timestamp": "2026-05-18T06:23:32.936798+00:00"
    },
    {
      "rank": 2,
      "user": "team_18",
      "github": "wbr258/openoperator-start-kit",
      "score": 0.011945109888522503,
      "latency": 17935.875182350475,
      "timestamp": "2026-05-18T06:39:14.747904+00:00"
    }
  ],
  "last_updated": "2026-05-18T06:44:32.716080+00:00"
}