{
  "problem_id": "064",
  "problem_name": "064_adaptive_average_pool_nhwc",
  "results": [
    {
      "rank": 1,
      "user": "cuda组",
      "github": "AICS-2025-63H/openoperator",
      "score": 0.7183547623597976,
      "latency": 45.95918580889702,
      "timestamp": "2026-05-17T16:49:21.975863+00:00"
    },
    {
      "rank": 2,
      "user": "team_70",
      "github": "SilWhite/ICS-Competition",
      "score": 0.19027624095297035,
      "latency": 173.51089045405388,
      "timestamp": "2026-05-17T17:15:47.803387+00:00"
    },
    {
      "rank": 3,
      "user": "team_90",
      "github": "sleepy3dog/AICS-38",
      "score": 0.027972893452301716,
      "latency": 1180.2497319877148,
      "timestamp": "2026-05-17T14:03:33.558845+00:00"
    },
    {
      "rank": 4,
      "user": "智算第七组",
      "github": "laomaer/BANGC07",
      "score": 0.02726491090335357,
      "latency": 1210.8970433473587,
      "timestamp": "2026-05-17T14:06:59.245930+00:00"
    },
    {
      "rank": 5,
      "user": "team_18",
      "github": "wbr258/openoperator-start-kit",
      "score": 0.00018798952344146357,
      "latency": 175621.4888766408,
      "timestamp": "2026-05-17T15:22:49.231807+00:00"
    }
  ],
  "last_updated": "2026-05-18T01:40:11.160960+00:00"
}
