{
  "problem_id": "073",
  "problem_name": "073_Power",
  "results": [
    {
      "rank": 1,
      "user": "team_70",
      "github": "SilWhite/ICS-Competition",
      "score": 0.017422413815435963,
      "latency": 2223.744678000609,
      "timestamp": "2026-05-18T09:16:37.878376+00:00"
    },
    {
      "rank": 2,
      "user": "team_91",
      "github": "PRO-2684/AICS-openoperator",
      "score": 0.016825095891526073,
      "latency": 2302.691185226043,
      "timestamp": "2026-05-18T08:24:31.012076+00:00"
    },
    {
      "rank": 3,
      "user": "team_42",
      "github": "PRO-2684/AICS-openoperator",
      "score": 0.016227631452064392,
      "latency": 2387.471031397581,
      "timestamp": "2026-05-18T08:46:03.641010+00:00"
    },
    {
      "rank": 4,
      "user": "二十四组",
      "github": "Hengyu-Yu/OpenOperator-Group24",
      "score": 0.01598673439362447,
      "latency": 2423.446780691544,
      "timestamp": "2026-05-18T07:07:14.408663+00:00"
    },
    {
      "rank": 5,
      "user": "team_55",
      "github": "geotle77/AICS-BangC_Game-17",
      "score": 0.015865370374799983,
      "latency": 2441.9852222005525,
      "timestamp": "2026-05-18T07:48:46.961584+00:00"
    },
    {
      "rank": 6,
      "user": "cuda组",
      "github": "AICS-2025-63H/openoperator",
      "score": 0.013683332816556579,
      "latency": 2831.400837749243,
      "timestamp": "2026-05-18T06:38:30.784519+00:00"
    },
    {
      "rank": 7,
      "user": "team_40",
      "github": "CCyyyydr/openoperator-32",
      "score": 0.011488529182323416,
      "latency": 3372.3202844460807,
      "timestamp": "2026-05-18T06:42:23.637274+00:00"
    },
    {
      "rank": 8,
      "user": "team_48",
      "github": "zhangxingyin/ICS_18Team",
      "score": 0.009133420454231718,
      "latency": 4241.893844058116,
      "timestamp": "2026-05-18T07:48:39.216921+00:00"
    },
    {
      "rank": 9,
      "user": "team_86",
      "github": "RachelGu2003/ICS_86Team",
      "score": 0.003549342251146292,
      "latency": 10915.543573598066,
      "timestamp": "2026-05-18T05:56:16.035262+00:00"
    },
    {
      "rank": 10,
      "user": "team_43",
      "github": "Demoxxy/smart_openoperator-start-kit",
      "score": 0.003450656785332711,
      "latency": 11227.717623114586,
      "timestamp": "2026-05-18T07:37:27.435116+00:00"
    },
    {
      "rank": 11,
      "user": "team_18",
      "github": "wbr258/openoperator-start-kit",
      "score": 0.0004121471232459936,
      "latency": 94002.83979872863,
      "timestamp": "2026-05-18T06:58:47.646364+00:00"
    }
  ],
  "last_updated": "2026-05-18T09:17:07.566625+00:00"
}