{
  "problem_id": "074",
  "problem_name": "074_Std_reduction_over_dim",
  "results": [
    {
      "rank": 1,
      "user": "team_42",
      "github": "PRO-2684/AICS-openoperator",
      "score": 0.2782685141737192,
      "latency": 376.8410533666611,
      "timestamp": "2026-06-04T19:19:16.124248+00:00",
      "commit_sha": "5054c52c63873af0b05219e8741b6479f441dff9"
    },
    {
      "rank": 2,
      "user": "team_91",
      "github": "PRO-2684/AICS-openoperator",
      "score": 0.26817183540265466,
      "latency": 391.02913190921146,
      "timestamp": "2026-06-05T03:55:36.770858+00:00",
      "commit_sha": "5054c52c63873af0b05219e8741b6479f441dff9"
    },
    {
      "rank": 3,
      "user": "十六组",
      "github": "Cek2001/BangC16",
      "score": 0.042690597381752196,
      "latency": 2456.348855048418,
      "timestamp": "2026-06-03T14:09:56.114711+00:00"
    },
    {
      "rank": 4,
      "user": "智算第八组",
      "github": "beiwenziyao/BANGC08",
      "score": 0.04264607811787865,
      "latency": 2458.913096537193,
      "timestamp": "2026-05-19T15:32:57.999197+00:00",
      "commit_sha": "eabed1c1d4d29db09016ce9166cad1f7c6fba4ec"
    },
    {
      "rank": 5,
      "user": "team_18",
      "github": "wbr258/openoperator-start-kit",
      "score": 0.04199944566495685,
      "latency": 2496.7710487544537,
      "timestamp": "2026-05-18T06:37:58.495503+00:00",
      "commit_sha": "ca33177ed60523bbddb5c4e583d4ff1d9d2b84a8"
    },
    {
      "rank": 6,
      "user": "不懂算子",
      "github": "HeiHuDie/openoperator-competition-p",
      "score": 0.041194445379870895,
      "latency": 2545.5616414546967,
      "timestamp": "2026-06-10T13:52:43.138493+00:00"
    },
    {
      "rank": 7,
      "user": "十五组",
      "github": "fengjin1126/BangC15",
      "score": 0.04029259466105969,
      "latency": 2602.537783483664,
      "timestamp": "2026-06-09T00:52:08.716595+00:00"
    },
    {
      "rank": 8,
      "user": "三十二组",
      "github": "zhengbanlinyi/BangC32",
      "score": 0.03961168387501847,
      "latency": 2647.2744842370353,
      "timestamp": "2026-06-09T13:45:00.114026+00:00"
    },
    {
      "rank": 9,
      "user": "team_55",
      "github": "geotle77/AICS-BangC_Game-17",
      "score": 0.039471490704582064,
      "latency": 2656.6769617299237,
      "timestamp": "2026-05-18T07:29:54.846671+00:00",
      "commit_sha": "a6609cd5cc0cfc49bd2e156bd0071082f1bbccb0"
    },
    {
      "rank": 10,
      "user": "team_90",
      "github": "sleepy3dog/AICS-38",
      "score": 0.038324747289762776,
      "latency": 2736.1693792045116,
      "timestamp": "2026-06-02T03:23:23.701099+00:00",
      "commit_sha": "0341c165f3c6454e3e29c5f79646bbc38ca22ac6"
    },
    {
      "rank": 11,
      "user": "cuda组",
      "github": "AICS-2025-63H/openoperator",
      "score": 0.03237764429549472,
      "latency": 3238.7470516065755,
      "timestamp": "2026-05-18T07:09:39.211907+00:00",
      "commit_sha": "e16081205aa0f296d792fb3a2fc705cd02c1ac09"
    },
    {
      "rank": 12,
      "user": "智算第七组",
      "github": "laomaer/BANGC07",
      "score": 0.023627822463662365,
      "latency": 4438.115283846855,
      "timestamp": "2026-06-02T08:19:24.100385+00:00"
    },
    {
      "rank": 13,
      "user": "二十一组",
      "github": "ouligei6666/y-team-21-openoperator-start-kit",
      "score": 0.022440589533965733,
      "latency": 4672.916450848182,
      "timestamp": "2026-05-28T14:26:03.534767+00:00"
    },
    {
      "rank": 14,
      "user": "智算第十组",
      "github": "koross49/openoperator-start-kit",
      "score": 0.017210352596164453,
      "latency": 6093.018688261509,
      "timestamp": "2026-06-08T12:17:29.249186+00:00"
    },
    {
      "rank": 15,
      "user": "team_48",
      "github": "zhangxingyin/ICS_18Team",
      "score": 0.017049500653555122,
      "latency": 6150.5027115345,
      "timestamp": "2026-05-18T14:36:40.112566+00:00",
      "commit_sha": "a7123fbeb31fc6930f6c2018affca3abfab1ed7d"
    },
    {
      "rank": 16,
      "user": "team_60",
      "github": "shadowcathh/openoperator-start-kit",
      "score": 0.0138797066280065,
      "latency": 7555.130869150162,
      "timestamp": "2026-05-29T14:29:05.849858+00:00"
    },
    {
      "rank": 17,
      "user": "888",
      "github": "RuiXiZhang03/888-op-gen",
      "score": 0.013409894334192544,
      "latency": 7819.8229894042015,
      "timestamp": "2026-06-08T16:57:28.342374+00:00"
    },
    {
      "rank": 18,
      "user": "智算第九组",
      "github": "XLS233/BangC09",
      "score": 0.00501910573204554,
      "latency": 20892.76568343242,
      "timestamp": "2026-06-05T14:43:21.076420+00:00"
    },
    {
      "rank": 19,
      "user": "team_8",
      "github": "ykkkx/ICS_28",
      "score": 0.004103198010017097,
      "latency": 25556.407403200865,
      "timestamp": "2026-05-25T10:07:27.962951+00:00"
    },
    {
      "rank": 20,
      "user": "team_27",
      "github": "JerryLiu369/openoperator-start-kit-theory",
      "score": 0.00401956483513588,
      "latency": 26088.147424161434,
      "timestamp": "2026-06-05T09:12:29.157367+00:00"
    },
    {
      "rank": 21,
      "user": "team_70",
      "github": "SilWhite/ICS-Competition",
      "score": 0.003890212873780156,
      "latency": 26955.594308674335,
      "timestamp": "2026-05-18T09:00:34.120470+00:00",
      "commit_sha": "14cee49804ac595b52e7a9a34fafba505e1406b1"
    },
    {
      "rank": 22,
      "user": "team_86",
      "github": "RachelGu2003/ICS_86Team",
      "score": 0.0038245046339131826,
      "latency": 27418.714327116806,
      "timestamp": "2026-06-10T11:46:24.215945+00:00",
      "commit_sha": "8228f2be1c965c2ec0731de89804b73f6846a63e"
    },
    {
      "rank": 23,
      "user": "team_25",
      "github": "zion-zion-zion/openoperator-start-kit",
      "score": 0.0036736857498070315,
      "latency": 28544.357667366665,
      "timestamp": "2026-06-09T10:07:42.531987+00:00"
    },
    {
      "rank": 24,
      "user": "team_73",
      "github": "dingyue772/TensorCraft",
      "score": 0.002385581230047278,
      "latency": 43957.00246095657,
      "timestamp": "2026-05-18T09:22:18.533107+00:00",
      "commit_sha": "14b60371e4d17652d07d516ff3c8beff70870f1d"
    },
    {
      "rank": 25,
      "user": "二十四组",
      "github": "Hengyu-Yu/OpenOperator-Group24",
      "score": 0.001996135912335367,
      "latency": 52532.99605101347,
      "timestamp": "2026-06-03T14:51:06.469059+00:00"
    },
    {
      "rank": 26,
      "user": "team_36",
      "github": "luogarden/Team35_BANGC",
      "score": 0.0009382779218212707,
      "latency": 111761.129150788,
      "timestamp": "2026-06-09T03:07:10.533849+00:00"
    },
    {
      "rank": 27,
      "user": "不知道叫什么名字组",
      "github": "luoluoluoluoli/Luoluoli_ice1",
      "score": 0.00048780402297324304,
      "latency": 214969.52682112655,
      "timestamp": "2026-06-01T00:08:25.870261+00:00"
    }
  ],
  "last_updated": "2026-06-10T13:56:42.997656+00:00"
}