{
  "problem_id": "083",
  "problem_name": "083_Causal_Self_Attention",
  "results": [
    {
      "rank": 1,
      "user": "cuda组",
      "github": "AICS-2025-63H/openoperator",
      "score": 5.752136752136752,
      "latency": 23.4,
      "timestamp": "2026-05-05T12:05:44.068201+00:00"
    },
    {
      "rank": 2,
      "user": "team_42",
      "github": "PRO-2684/AICS-openoperator",
      "score": 5.427419354838709,
      "latency": 24.8,
      "timestamp": "2026-05-06T19:00:21.429813+00:00"
    },
    {
      "rank": 3,
      "user": "team_91",
      "github": "PRO-2684/AICS-openoperator",
      "score": 5.427419354838709,
      "latency": 24.8,
      "timestamp": "2026-05-06T18:59:08.963585+00:00"
    },
    {
      "rank": 4,
      "user": "不懂算子",
      "github": "HeiHuDie/openoperator-competition",
      "score": 0.6052158273381295,
      "latency": 222.4,
      "timestamp": "2026-05-04T17:26:12.916166+00:00"
    },
    {
      "rank": 5,
      "user": "team_48",
      "github": "zhangxingyin/ICS_18Team",
      "score": 0.12662276575729067,
      "latency": 1063.0,
      "timestamp": "2026-05-02T02:50:15.266279+00:00"
    },
    {
      "rank": 6,
      "user": "team_25",
      "github": "zion-zion-zion/openoperator-start-kit",
      "score": 0.0006671636523690752,
      "latency": 201749.6,
      "timestamp": "2026-04-29T06:28:00.056563+00:00"
    },
    {
      "rank": 7,
      "user": "team_90",
      "github": "sleepy3dog/AICS-38",
      "score": 0.00044273111814276594,
      "latency": 304022.0,
      "timestamp": "2026-04-29T14:17:14.243566+00:00"
    }
  ],
  "last_updated": "2026-05-06T19:00:42.496951+00:00"
}