{
  "problem_id": "093",
  "problem_name": "093_Batch_triangular_solve",
  "results": [
    {
      "rank": 1,
      "user": "team_91",
      "github": "PRO-2684/AICS-openoperator",
      "score": 1.8654697722961942,
      "latency": 42.4681231379509,
      "timestamp": "2026-05-17T14:55:34.591547+00:00"
    },
    {
      "rank": 2,
      "user": "team_42",
      "github": "PRO-2684/AICS-openoperator",
      "score": 1.8101488405340325,
      "latency": 43.76601427793503,
      "timestamp": "2026-05-17T14:01:29.935569+00:00"
    },
    {
      "rank": 3,
      "user": "team_18",
      "github": "wbr258/openoperator-start-kit",
      "score": 0.4372591376274574,
      "latency": 181.1808906495571,
      "timestamp": "2026-05-17T13:58:44.947604+00:00"
    },
    {
      "rank": 4,
      "user": "team_90",
      "github": "sleepy3dog/AICS-38",
      "score": 0.07853990600768955,
      "latency": 1008.6974129080772,
      "timestamp": "2026-05-17T15:05:35.494190+00:00"
    }
  ],
  "last_updated": "2026-05-17T15:08:55.715063+00:00"
}