{
  "problem_id": "095",
  "problem_name": "095_Add_RMSNorm",
  "results": [
    {
      "rank": 1,
      "user": "team_91",
      "github": "PRO-2684/AICS-openoperator",
      "score": 0.13502630420398154,
      "latency": 2666.673002143701,
      "timestamp": "2026-05-18T08:52:17.036007+00:00"
    },
    {
      "rank": 2,
      "user": "team_18",
      "github": "wbr258/openoperator-start-kit",
      "score": 0.12787333176764773,
      "latency": 2815.841231495142,
      "timestamp": "2026-05-18T06:38:11.954118+00:00"
    },
    {
      "rank": 3,
      "user": "team_42",
      "github": "PRO-2684/AICS-openoperator",
      "score": 0.11709946776647305,
      "latency": 3074.91576919953,
      "timestamp": "2026-05-18T08:46:03.641010+00:00"
    },
    {
      "rank": 4,
      "user": "cuda组",
      "github": "AICS-2025-63H/openoperator",
      "score": 0.11170674277142702,
      "latency": 3223.3595848083496,
      "timestamp": "2026-05-18T08:43:30.078519+00:00"
    },
    {
      "rank": 5,
      "user": "team_70",
      "github": "SilWhite/ICS-Competition",
      "score": 0.0880757512843331,
      "latency": 4088.1967482467494,
      "timestamp": "2026-05-18T09:00:34.120470+00:00"
    }
  ],
  "last_updated": "2026-05-18T09:01:53.304544+00:00"
}