{
  "problem_id": "101",
  "problem_name": "101_Max_Pool_2D_with_indices",
  "results": [
    {
      "rank": 1,
      "user": "team_42",
      "github": "PRO-2684/AICS-openoperator",
      "score": 0.7642122623730304,
      "latency": 684.4564341008663,
      "timestamp": "2026-05-19T08:28:06.560144+00:00",
      "commit_sha": "f973075041f662efa5574e7118884927f0aae4cd"
    },
    {
      "rank": 2,
      "user": "team_91",
      "github": "PRO-2684/AICS-openoperator",
      "score": 0.7449310566652202,
      "latency": 702.1723625560602,
      "timestamp": "2026-05-19T08:28:01.907445+00:00",
      "commit_sha": "d6bcc18b6600da76773241af74d69cfa46d11677"
    },
    {
      "rank": 3,
      "user": "cuda组",
      "github": "AICS-2025-63H/openoperator",
      "score": 0.21021503912123532,
      "latency": 2488.261554390192,
      "timestamp": "2026-05-18T09:41:07.584422+00:00",
      "commit_sha": "55b30331cca73c1347cb94835c265143dc404e70"
    },
    {
      "rank": 4,
      "user": "team_70",
      "github": "SilWhite/ICS-Competition",
      "score": 0.159949923295587,
      "latency": 3270.2110086878142,
      "timestamp": "2026-05-18T09:00:34.120470+00:00",
      "commit_sha": "14cee49804ac595b52e7a9a34fafba505e1406b1"
    }
  ],
  "last_updated": "2026-05-19T08:33:21.589415+00:00"
}