{
  "problem_id": "108",
  "problem_name": "108_ALiBi_attention_bias",
  "results": [
    {
      "rank": 1,
      "user": "team_48",
      "github": "zhangxingyin/ICS_18Team",
      "score": 3.3248407643312103,
      "latency": 31.4,
      "timestamp": "2026-04-29T15:06:02.417038+00:00"
    },
    {
      "rank": 2,
      "user": "team_25",
      "github": "zion-zion-zion/openoperator-start-kit",
      "score": 0.3252336448598131,
      "latency": 321.0,
      "timestamp": "2026-04-28T18:20:57.706271+00:00"
    }
  ],
  "last_updated": "2026-04-29T15:08:44.638071+00:00"
}