{
  "problem_id": "109",
  "problem_name": "109_Scatter_add",
  "results": [
    {
      "rank": 1,
      "user": "team_86",
      "github": "RachelGu2003/ICS_86Team",
      "score": 3.7340425531914896,
      "latency": 18.8,
      "timestamp": "2026-05-12T03:00:46.882234+00:00"
    },
    {
      "rank": 2,
      "user": "team_91",
      "github": "PRO-2684/AICS-openoperator",
      "score": 0.5161764705882353,
      "latency": 136.0,
      "timestamp": "2026-05-12T11:36:24.779918+00:00"
    },
    {
      "rank": 3,
      "user": "team_42",
      "github": "PRO-2684/AICS-openoperator",
      "score": 0.5154185022026432,
      "latency": 136.2,
      "timestamp": "2026-05-12T11:09:45.300342+00:00"
    },
    {
      "rank": 4,
      "user": "team_72",
      "github": "ifbluerain/kernel-competition-bot-openoperator-start-kit",
      "score": 0.12580645161290324,
      "latency": 558.0,
      "timestamp": "2026-05-08T06:43:45.257755+00:00"
    },
    {
      "rank": 5,
      "user": "team_29",
      "github": "duroey/openoperator-basic",
      "score": 0.01079136690647482,
      "latency": 6505.2,
      "timestamp": "2026-05-08T03:42:50.925322+00:00"
    },
    {
      "rank": 6,
      "user": "team_70",
      "github": "SilWhite/ICS-Competition",
      "score": 0.0009555700751388436,
      "latency": 73464.0,
      "timestamp": "2026-05-07T11:56:33.891543+00:00"
    },
    {
      "rank": 7,
      "user": "算不懂",
      "github": "caozhining/suanbudong_openoperator",
      "score": 0.0003764696797111802,
      "latency": 186469.2,
      "timestamp": "2026-05-10T08:53:34.966600+00:00"
    },
    {
      "rank": 8,
      "user": "team_12",
      "github": "yinuo222/kernel-competition-group40",
      "score": 8.503467282727932e-05,
      "latency": 825545.6,
      "timestamp": "2026-05-07T11:59:36.907113+00:00"
    },
    {
      "rank": 9,
      "user": "随缘组",
      "github": "xufeng102403/operator",
      "score": 8.482184392055745e-05,
      "latency": 827617.0,
      "timestamp": "2026-05-07T08:17:34.736664+00:00"
    },
    {
      "rank": 10,
      "user": "养老组",
      "github": "Ace-Eternal/op_retirement",
      "score": 8.470761994514519e-05,
      "latency": 828733.0,
      "timestamp": "2026-05-12T05:02:04.705273+00:00"
    },
    {
      "rank": 11,
      "user": "team_90",
      "github": "sleepy3dog/AICS-38",
      "score": 1.3963854542624884e-05,
      "latency": 5027265.2,
      "timestamp": "2026-05-07T09:02:17.011965+00:00"
    },
    {
      "rank": 12,
      "user": "team_49",
      "github": "drafter0364/AICS-30",
      "score": 6.072998900147026e-06,
      "latency": 11559363.2,
      "timestamp": "2026-05-08T09:16:56.383757+00:00"
    }
  ],
  "last_updated": "2026-05-12T11:38:02.472796+00:00"
}