{
  "problem_id": "134",
  "problem_name": "134_Depthwise_conv_2D",
  "results": [
    {
      "rank": 1,
      "user": "team_91",
      "github": "PRO-2684/AICS-openoperator",
      "score": 1.9453581871345027,
      "latency": 547.2,
      "timestamp": "2026-05-11T16:53:13.641253+00:00"
    },
    {
      "rank": 2,
      "user": "team_42",
      "github": "PRO-2684/AICS-openoperator",
      "score": 1.9361586031284106,
      "latency": 549.8,
      "timestamp": "2026-05-14T19:03:23.830068+00:00"
    }
  ],
  "last_updated": "2026-05-14T19:08:32.896062+00:00"
}